bicchiere.py
bicchiere-1.9.5.dist-info/LICENSE
bicchiere-1.9.5.dist-info/METADATA
bicchiere-1.9.5.dist-info/WHEEL
bicchiere-1.9.5.dist-info/entry_points.txt
bicchiere-1.9.5.dist-info/top_level.txt
bicchiere-1.9.5.dist-info/RECORD
