Metadata-Version: 2.1
Name: bicchiere
Version: 1.9.5
Summary: Yet another python web (WSGI) micro-framework
Author-email: Domingo E Savoretti <esavoretti@gmail.com>
License: MIT License        
Project-URL: Homepage, https://github.com/sandy98/bicchiere
Project-URL: Wiki, https://github.com/sandy98/bicchiere/wiki
Project-URL: Demo, https://bicchiere.sytes.net
Keywords: web,wsgi,app,middleware,server,session,templates,WebSocket
Classifier: License :: OSI Approved :: MIT License
Classifier: Programming Language :: Python
Classifier: Programming Language :: Python :: 3
Requires-Python: >=3.6
License-File: LICENSE
